znmdakit/__init__.py
znmdakit/transformations.py
znmdakit/utils.py
znmdakit/nodes/__init__.py
znmdakit/nodes/density.py
znmdakit/nodes/ionic_conductivity.py
znmdakit/nodes/mean_square_displacement.py
znmdakit/nodes/radial_distribution_function.py
znmdakit/nodes/universe.py
znmdakit/nodes/write_xyz.py
znmdakit-0.1.1.dist-info/METADATA
znmdakit-0.1.1.dist-info/WHEEL
znmdakit-0.1.1.dist-info/licenses/LICENSE
znmdakit-0.1.1.dist-info/RECORD
