Metadata-Version: 2.4
Name: znmdakit
Version: 0.1.1
Summary: MD post processing tools.
Author-email: Fabian Zills <fzills@icp.uni-stuttgart.de>
License-Expression: Apache-2.0
License-File: LICENSE
Requires-Python: >=3.10
Requires-Dist: ase>=3.24.0
Requires-Dist: mdanalysis>=2.8.0
Requires-Dist: pandas>=2.2.3
Requires-Dist: pint>=0.23.0
Requires-Dist: rdkit2ase>=0.1.4
Requires-Dist: scipy>=1.15.1
Requires-Dist: seaborn>=0.13.2
Requires-Dist: tidynamics>=1.1.2
Requires-Dist: znh5md>=0.4.3
Requires-Dist: zntrack>=0.8.4
